tomato_omega/__init__.py
tomato_omega-1.0.dist-info/licenses/LICENSE
tomato_omega-1.0.dist-info/METADATA
tomato_omega-1.0.dist-info/WHEEL
tomato_omega-1.0.dist-info/top_level.txt
tomato_omega-1.0.dist-info/RECORD
