Metadata-Version: 2.4
Name: tomato-omega
Version: 1.0
Summary: This package is a part of tomato. It has been made for the automation of Omega *USBH pressure transducers.
Author-email: Peter Kraus <peter.kraus@ceramics.tu-berlin.de>
Project-URL: Homepage, https://github.com/dgbowl/tomato-omega
Project-URL: Bug Tracker, https://github.com/dgbowl/tomato-omega/issues
Classifier: Development Status :: 3 - Alpha
Classifier: License :: OSI Approved :: GNU General Public License v3 or later (GPLv3+)
Classifier: Programming Language :: Python :: 3.10
Classifier: Programming Language :: Python :: 3.11
Classifier: Programming Language :: Python :: 3.12
Classifier: Programming Language :: Python :: 3.13
Classifier: Programming Language :: Python :: 3.14
Classifier: Operating System :: OS Independent
Requires-Python: >=3.10
License-File: LICENSE
Requires-Dist: tomato>=2.2rc2
Requires-Dist: pyserial>=3.5
Provides-Extra: testing
Requires-Dist: pytest; extra == "testing"
Dynamic: license-file
